cpdflow/__init__.py
cpdflow/cli.py
cpdflow/config.py
cpdflow/graph.py
cpdflow/version.py
cpdflow/lifecycle/__init__.py
cpdflow/lifecycle/deploy.py
cpdflow/lifecycle/develop.py
cpdflow/lifecycle/subscribe.py
cpdflow/model/__init__.py
cpdflow/model/model.py
cpdflow/utils/__init__.py
cpdflow/utils/logging_utils.py
cpdflow/wkc/__init__.py
cpdflow/wkc/wkc.py
cpdflow/wml/__init__.py
cpdflow/wml/wml.py
cpdflow/wos/__init__.py
cpdflow/wos/wos.py
cpdflow/ws/__init__.py
cpdflow/ws/ws.py
cpdflow-0.0.15.dist-info/LICENSE
cpdflow-0.0.15.dist-info/METADATA
cpdflow-0.0.15.dist-info/WHEEL
cpdflow-0.0.15.dist-info/entry_points.txt
cpdflow-0.0.15.dist-info/top_level.txt
cpdflow-0.0.15.dist-info/RECORD
