Metadata-Version: 2.1
Name: cpdflow
Version: 0.0.15
Summary: A declarative approach to model lifecycle management on Cloud Pak for Data
Home-page: https://github.com/randyphoa/cpdflow
Author: Randy Phoa
License: GPLv3
Platform: UNKNOWN
Classifier: Development Status :: 3 - Alpha
Classifier: Intended Audience :: Developers
Classifier: Programming Language :: Python :: 3.7
License-File: LICENSE
Requires-Dist: click
Requires-Dist: mlflow
Requires-Dist: networkx
Requires-Dist: scikit-learn
Requires-Dist: ibm-watson-openscale
Requires-Dist: ibm-watson-machine-learning
Requires-Dist: ibm-aigov-facts-client
